immuta_audit_export/.DS_Store
immuta_audit_export/__init__.py
immuta_audit_export/common/__init__.py
immuta_audit_export/common/call_export_record.py
immuta_audit_export/common/config_schemas/s3_config.py
immuta_audit_export/export_all.py
immuta_audit_export/export_record/__init__.py
immuta_audit_export/export_record/export_record_registry.py
immuta_audit_export/export_record/s3_export_record.py
immuta_audit_export/main.py
immuta_audit_export/tenant_config/__init__.py
immuta_audit_export/tenant_config/get_tenant_configs.py
immuta_audit_export/tenant_config/planning.md
immuta_audit_export-0.1.10.dist-info/WHEEL
immuta_audit_export-0.1.10.dist-info/METADATA
immuta_audit_export-0.1.10.dist-info/RECORD
